tool_box-0.5.1.dist-info/DESCRIPTION.rst
tool_box-0.5.1.dist-info/entry_points.txt
tool_box-0.5.1.dist-info/WHEEL
tool_box-0.5.1.dist-info/METADATA
tool_box-0.5.1.dist-info/top_level.txt
tool_box-0.5.1.dist-info/RECORD
tool_box-0.5.1.dist-info/metadata.json
toolbox/utils.py
toolbox/scanner.py
toolbox/defaults.py
toolbox/config.py
toolbox/plugin.py
toolbox/core.py
toolbox/registry.py
toolbox/cli.py
toolbox/__init__.py
toolbox/mixins.py
toolbox/contrib/__init__.py
toolbox/contrib/create/renderer.py
toolbox/contrib/create/create.py
toolbox/contrib/create/parser.py
toolbox/contrib/create/__init__.py
toolbox/contrib/create/templates/default.zip
toolbox/contrib/create/templates/shell.zip
toolbox/contrib/checksum/__init__.py
toolbox/contrib/checksum/checksum.py
toolbox/contrib/install/__init__.py
toolbox/contrib/install/install.py
toolbox/contrib/config/config.py
toolbox/contrib/config/__init__.py
toolbox/contrib/logs/logs.py
toolbox/contrib/logs/__init__.py
toolbox/contrib/list/__init__.py
toolbox/contrib/list/list.py
tests/test_scanner.py
tests/test_toolbox.py
tests/test_registry.py
tests/test_config.py
tests/plugin_module.py
tests/__init__.py
