Metadata-Version: 2.0
Name: tool-box
Version: 0.5.1
Summary: tools for your toolbox , neatly organised
Home-page: http://github.com/jeff-99/toolbox
Author: Jeff Slort
Author-email: j_slort@hotmail.com
License: MIT
Keywords: toolbox
Platform: UNKNOWN
Requires-Dist: terminaltables
